cloudrender/__init__.py
cloudrender/capturing.py
cloudrender/scene.py
cloudrender/utils.py
cloudrender/camera/__init__.py
cloudrender/camera/models.py
cloudrender/camera/trajectory.py
cloudrender/libegl/__init__.py
cloudrender/libegl/context.py
cloudrender/libegl/libgbm.py
cloudrender/libegl/tools.py
cloudrender/libegl/devices/__init__.py
cloudrender/libegl/devices/gbm.py
cloudrender/libegl/devices/generic.py
cloudrender/render/__init__.py
cloudrender/render/depthmap.py
cloudrender/render/lights.py
cloudrender/render/mesh.py
cloudrender/render/pointcloud.py
cloudrender/render/renderable.py
cloudrender/render/rigid.py
cloudrender/render/shadowmap.py
cloudrender/render/smpl.py
cloudrender/render/smpl_legacy.py
cloudrender/render/utils.py
cloudrender/render/shaders/__init__.py
cloudrender/render/shaders/shader_loader.py
cloudrender/render/shaders/avgcolor_pointcloud_with_normals/fragment.glsl
cloudrender/render/shaders/avgcolor_pointcloud_with_normals/geometry.glsl
cloudrender/render/shaders/avgcolor_pointcloud_with_normals/vertex_perspective.glsl
cloudrender/render/shaders/avgcolor_pointcloud_with_normals/depthmap/fragment.glsl
cloudrender/render/shaders/avgcolor_pointcloud_with_normals/depthmap/geometry.glsl
cloudrender/render/shaders/avgcolor_pointcloud_with_normals/depthmap/vertex_perspective.glsl
cloudrender/render/shaders/avgcolor_pointcloud_with_normals/normalization/fragment.glsl
cloudrender/render/shaders/avgcolor_pointcloud_with_normals/normalization/vertex.glsl
cloudrender/render/shaders/simple_mesh/fragment.glsl
cloudrender/render/shaders/simple_mesh/vertex_opencv.glsl
cloudrender/render/shaders/simple_mesh/vertex_perspective.glsl
cloudrender/render/shaders/simple_mesh/shadowdraw/fragment.glsl
cloudrender/render/shaders/simple_mesh/shadowdraw/vertex_opencv.glsl
cloudrender/render/shaders/simple_mesh/shadowdraw/vertex_perspective.glsl
cloudrender/render/shaders/simple_mesh/shadowgen/fragment.glsl
cloudrender-1.3.5.dist-info/LICENSE.md
cloudrender-1.3.5.dist-info/METADATA
cloudrender-1.3.5.dist-info/WHEEL
cloudrender-1.3.5.dist-info/top_level.txt
cloudrender-1.3.5.dist-info/RECORD
