Metadata-Version: 2.1
Name: cloudrender
Version: 1.3.5
Summary: An OpenGL framework for pointcloud and mesh rendering
Home-page: https://github.com/vguzov/cloudrender
Author: Vladimir Guzov
Author-email: vguzov@mpi-inf.mpg.de
Keywords: rendering,pointcloud,opengl,mesh
Classifier: Intended Audience :: Developers
Classifier: License :: Other/Proprietary License
Classifier: Natural Language :: English
Classifier: Operating System :: Unix
Classifier: Programming Language :: Python
Classifier: Programming Language :: Python :: 3
License-File: LICENSE.md
Requires-Dist: numpy
Requires-Dist: scipy
Requires-Dist: pyglm >=2.2.0
Requires-Dist: trimesh
Requires-Dist: torch
Requires-Dist: tqdm
Requires-Dist: smplpytorch
Requires-Dist: chumpy
Requires-Dist: PyOpenGL ==3.1.5
Requires-Dist: videoio >=0.2.3
